moloch_versioning/__init__.py
moloch_versioning/changelog_manager.py
moloch_versioning/config.py
moloch_versioning/hashing.py
moloch_versioning/name_generator.py
moloch_versioning/version_control_system.py
moloch_versioning/version_manager.py
moloch_versioning-0.1.dist-info/LICENSE
moloch_versioning-0.1.dist-info/METADATA
moloch_versioning-0.1.dist-info/WHEEL
moloch_versioning-0.1.dist-info/top_level.txt
moloch_versioning-0.1.dist-info/RECORD
