Metadata-Version: 2.1
Name: moloch_versioning
Version: 0.1
Summary: Automated version control system with customizable changelog and version management
Home-page: https://github.com/jamieres/Moloch.-Automated-Version-Control-Library
Author: Jorge Mieres
Author-email: Jorge Mieres <jamieres@gmail.com>
License: MIT License
Project-URL: Homepage, https://github.com/jamieres/Moloch.-Automated-Version-Control-Library
Project-URL: Issues, https://github.com/jamieres/Moloch.-Automated-Version-Control-Library/issues
Classifier: Programming Language :: Python :: 3
Classifier: License :: OSI Approved :: MIT License
Classifier: Operating System :: OS Independent
Requires-Python: >=3.7
License-File: LICENSE
